cratt/__init__.py
cratt/__main__.py
cratt/cli.py
cratt/cra.py
cratt/template.py
cratt/utils.py
cratt-1.6.4.dist-info/LICENSE
cratt-1.6.4.dist-info/METADATA
cratt-1.6.4.dist-info/WHEEL
cratt-1.6.4.dist-info/entry_points.txt
cratt-1.6.4.dist-info/top_level.txt
cratt-1.6.4.dist-info/RECORD
