Metadata-Version: 2.1
Name: cratt
Version: 1.6.4
Summary: A CLI for creating React App with TypeScript and TailwindCSS
Home-page: https://github.com/ccrsxx/cratt
Author: ccrsxx
Author-email: aminrisal@gmail.com
Project-URL: Bug Tracker, https://github.com/ccrsxx/cratt/issues
Classifier: Programming Language :: Python :: 3
Classifier: License :: OSI Approved :: MIT License
Classifier: Operating System :: OS Independent
Requires-Python: >=3.6
License-File: LICENSE
